articom_sdk/__init__.py
articom_sdk/cli.py
articom_sdk/server.py
articom_sdk/skill.py
articom_sdk-0.1.1.dist-info/METADATA
articom_sdk-0.1.1.dist-info/WHEEL
articom_sdk-0.1.1.dist-info/entry_points.txt
articom_sdk-0.1.1.dist-info/RECORD
