Metadata-Version: 2.3
Name: articom-sdk
Version: 0.1.1
Summary: SDK for building and self-hosting skills for the Articom Agentic Marketplace.
License: MIT
Keywords: articom,ai,agent,marketplace,sdk,skills
Author: Articom Inc.
Requires-Python: >=3.9,<4.0
Classifier: Development Status :: 3 - Alpha
Classifier: Intended Audience :: Developers
Classifier: License :: OSI Approved :: MIT License
Classifier: Programming Language :: Python :: 3
Classifier: Programming Language :: Python :: 3.9
Classifier: Programming Language :: Python :: 3.10
Classifier: Programming Language :: Python :: 3.11
Classifier: Programming Language :: Python :: 3.12
Classifier: Programming Language :: Python :: 3.13
Classifier: Topic :: Internet :: WWW/HTTP :: HTTP Servers
Classifier: Topic :: Scientific/Engineering :: Artificial Intelligence
Classifier: Topic :: Software Development :: Libraries :: Python Modules
Requires-Dist: fastapi (>=0.111.0,<0.112.0)
Requires-Dist: pydantic (>=2.7.1,<3.0.0)
Requires-Dist: python-dotenv (>=1.0.1,<2.0.0)
Requires-Dist: typer[all] (>=0.12.3,<0.13.0)
Requires-Dist: uvicorn[standard] (>=0.29.0,<0.30.0)
Project-URL: Documentation, https://github.com/Inforwaves/articom-skill-sdk-python
Project-URL: Homepage, https://github.com/Inforwaves/articom-skill-sdk-python
Project-URL: Repository, https://github.com/Inforwaves/articom-skill-sdk-python
